pyphd/__about__.py
pyphd/__init__.py
pyphd/__main__.py
pyphd/parser.py
pyphd/template.py
pyphd-1.0.0.dist-info/METADATA
pyphd-1.0.0.dist-info/WHEEL
pyphd-1.0.0.dist-info/entry_points.txt
pyphd-1.0.0.dist-info/licenses/LICENSE
pyphd-1.0.0.dist-info/RECORD
