Metadata-Version: 2.4
Name: pyphd
Version: 1.0.0
Summary: Create an opinionated python project structure.
Project-URL: Homepage, https://github.com/phdenzel/pyphd.git
Project-URL: Repository, https://github.com/phdenzel/pyphd.git
Project-URL: Documentation, https://github.com/phdenzel/pyphd#readme
Project-URL: Issues, https://github.com/phdenzel/pyphd/issues
Project-URL: Source, https://github.com/phdenzel/pyphd
Author-email: Philipp Denzel <phdenzel@gmail.com>
Maintainer-email: Philipp Denzel <phdenzel@gmail.com>
License:                     GNU GENERAL PUBLIC LICENSE
License-File: LICENSE
Classifier: License :: OSI Approved :: MIT License
Classifier: Operating System :: OS Independent
Classifier: Programming Language :: Python :: 3
Classifier: Programming Language :: Python :: 3.10
Classifier: Programming Language :: Python :: 3.11
Classifier: Programming Language :: Python :: 3.12
Classifier: Programming Language :: Python :: Implementation :: CPython
Classifier: Programming Language :: Python :: Implementation :: PyPy
Requires-Python: >=3.10
Requires-Dist: gitpython
Requires-Dist: python-dotenv
Provides-Extra: dev
Requires-Dist: pre-commit; extra == 'dev'
Requires-Dist: pytest; extra == 'dev'
Requires-Dist: pytest-cov; extra == 'dev'
Requires-Dist: ruff; extra == 'dev'
